habrahabr/__init__.py
habrahabr/api.py
habrahabr/auth.py
habrahabr/errors.py
habrahabr/utils.py
habrahabr/resources/__init__.py
habrahabr/resources/base.py
habrahabr/resources/comments.py
habrahabr/resources/company.py
habrahabr/resources/feed.py
habrahabr/resources/flow.py
habrahabr/resources/hub.py
habrahabr/resources/poll.py
habrahabr/resources/post.py
habrahabr/resources/search.py
habrahabr/resources/settings.py
habrahabr/resources/tracker.py
habrahabr/resources/user.py
habrahabr_api-0.1.2.dist-info/DESCRIPTION.rst
habrahabr_api-0.1.2.dist-info/METADATA
habrahabr_api-0.1.2.dist-info/RECORD
habrahabr_api-0.1.2.dist-info/WHEEL
habrahabr_api-0.1.2.dist-info/metadata.json
habrahabr_api-0.1.2.dist-info/top_level.txt
