Metadata-Version: 2.0
Name: habrahabr-api
Version: 0.1.2
Summary: A python implementation of the Habrahabr.ru API
Home-page: https://github.com/dotzero/habrahabr-api-python
Author: dotzero
Author-email: mail@dotzero.ru
License: MIT
Platform: UNKNOWN
